aurelio/__init__.py
aurelio/_dict.py
aurelio/clients/__init__.py
aurelio/clients/abstract_client.py
aurelio/clients/redis_client.py
aurelio/exceptions.py
aurelio/settings/__init__.py
aurelio/settings/redis_settings.py
aurelio/utils.py
aurelio-0.0.1.dist-info/LICENSE
aurelio-0.0.1.dist-info/WHEEL
aurelio-0.0.1.dist-info/METADATA
aurelio-0.0.1.dist-info/RECORD
