Metadata-Version: 2.1
Name: aurelio
Version: 0.0.1
Summary: Python dictionary interface for key-value databases
License: MIT
Author: KelvinS
Author-email: kelvinpfw@gmail.com
Requires-Python: >=3.7,<4.0
Classifier: License :: OSI Approved :: MIT License
Classifier: Programming Language :: Python :: 3
Classifier: Programming Language :: Python :: 3.10
Classifier: Programming Language :: Python :: 3.7
Classifier: Programming Language :: Python :: 3.8
Classifier: Programming Language :: Python :: 3.9
Provides-Extra: redis
Requires-Dist: redis (>=4.1.4,<5.0.0); extra == "redis"
